mmry/__init__.py
mmry/client.py
mmry/config.py
mmry/errors.py
mmry/factory.py
mmry/memory_manager.py
mmry/base/llm_base.py
mmry/base/vectordb_base.py
mmry/embedding/embedding_base.py
mmry/embedding/local_embedding.py
mmry/embedding/openrouter_embedding.py
mmry/llms/openrouter_base.py
mmry/llms/openrouter_context_builder.py
mmry/llms/openrouter_merger.py
mmry/llms/openrouter_summariser.py
mmry/utils/datetime.py
mmry/utils/decay.py
mmry/utils/health.py
mmry/utils/scoring.py
mmry/utils/text.py
mmry/vector_store/qdrant.py
mmry_ai-0.1.0.dist-info/licenses/LICENSE
mmry_ai-0.1.0.dist-info/METADATA
mmry_ai-0.1.0.dist-info/WHEEL
mmry_ai-0.1.0.dist-info/top_level.txt
mmry_ai-0.1.0.dist-info/RECORD
