Metadata-Version: 2.4
Name: mmry-ai
Version: 0.1.0
Summary: A memory management layer for AI agents using vector similarity search
Author-email: manavnotop <manuagarwal1443@gmail.com>
License-Expression: MIT
Classifier: Programming Language :: Python :: 3.13
Classifier: Intended Audience :: Developers
Classifier: Topic :: Scientific/Engineering :: Artificial Intelligence
Requires-Python: >=3.13
License-File: LICENSE
Requires-Dist: dotenv>=0.9.9
Requires-Dist: pydantic>=2.12.4
Requires-Dist: qdrant-client>=1.15.1
Requires-Dist: requests>=2.32.3
Requires-Dist: sentence-transformers>=5.1.2
Requires-Dist: tenacity>=8.2.0
Dynamic: license-file
